SHGS/__init__.py
SHGS/example.py
SHGS-2.0.0.dist-info/LICENSE
SHGS-2.0.0.dist-info/METADATA
SHGS-2.0.0.dist-info/WHEEL
SHGS-2.0.0.dist-info/top_level.txt
SHGS-2.0.0.dist-info/RECORD
