Metadata-Version: 2.1
Name: SHGS
Version: 2.0.0
Summary: single-hyperparameter-grid-search(shgs)
Author: Xia Jiang, Yijun
Author-email: xij6@pitt.edu
Classifier: Programming Language :: Python :: 3
Classifier: License :: OSI Approved :: MIT License
Classifier: Operating System :: OS Independent
Requires-Python: ==3.7
License-File: LICENSE
Requires-Dist: scikit-learn
Requires-Dist: numpy
Requires-Dist: keras (==2.6.0)
Requires-Dist: tensorflow (==2.6.0)
